llm_fireworks.py
llm_fireworks-0.1a0.dist-info/LICENSE
llm_fireworks-0.1a0.dist-info/METADATA
llm_fireworks-0.1a0.dist-info/WHEEL
llm_fireworks-0.1a0.dist-info/entry_points.txt
llm_fireworks-0.1a0.dist-info/top_level.txt
llm_fireworks-0.1a0.dist-info/RECORD
