Metadata-Version: 2.1
Name: llm-fireworks
Version: 0.1a0
Summary: Access fireworks.ai models via API
Author: Simon Willison
License: Apache-2.0
Project-URL: Homepage, https://github.com/simonw/llm-fireworks
Project-URL: Changelog, https://github.com/simonw/llm-fireworks/releases
Project-URL: Issues, https://github.com/simonw/llm-fireworks/issues
Project-URL: CI, https://github.com/simonw/llm-fireworks/actions
Classifier: License :: OSI Approved :: Apache Software License
License-File: LICENSE
Requires-Dist: llm
Provides-Extra: test
Requires-Dist: pytest ; extra == 'test'
